business_rules_reasoning/__init__.py
business_rules_reasoning/json_deserializer.py
business_rules_reasoning/json_serializer.py
business_rules_reasoning/base/__init__.py
business_rules_reasoning/base/conclusion.py
business_rules_reasoning/base/knowledge_base.py
business_rules_reasoning/base/operator_enums.py
business_rules_reasoning/base/predicate.py
business_rules_reasoning/base/reasoning_enums.py
business_rules_reasoning/base/reasoning_process.py
business_rules_reasoning/base/reasoning_service.py
business_rules_reasoning/base/rule.py
business_rules_reasoning/base/variable.py
business_rules_reasoning/base/operators/__init__.py
business_rules_reasoning/base/operators/between.py
business_rules_reasoning/base/operators/equal.py
business_rules_reasoning/base/operators/greater_or_equal.py
business_rules_reasoning/base/operators/greater_than.py
business_rules_reasoning/base/operators/is_in.py
business_rules_reasoning/base/operators/less_or_equal.py
business_rules_reasoning/base/operators/less_than.py
business_rules_reasoning/base/operators/not_between.py
business_rules_reasoning/base/operators/not_equal.py
business_rules_reasoning/base/operators/not_in.py
business_rules_reasoning/base/operators/not_subset.py
business_rules_reasoning/base/operators/subset.py
business_rules_reasoning/base/value_types/__init__.py
business_rules_reasoning/base/value_types/base_type.py
business_rules_reasoning/base/value_types/list_type.py
business_rules_reasoning/deductive/__init__.py
business_rules_reasoning/deductive/deductive_conclusion.py
business_rules_reasoning/deductive/deductive_predicate.py
business_rules_reasoning/deductive/deductive_reasoning_service.py
business_rules_reasoning/deductive/knowledge_builder.py
business_rules_reasoning/deductive/decision_table/__init__.py
business_rules_reasoning/deductive/decision_table/c45_decision_tree.py
business_rules_reasoning/deductive/decision_table/decision_table_to_ruleset.py
business_rules_reasoning-0.2.0.dist-info/METADATA
business_rules_reasoning-0.2.0.dist-info/WHEEL
business_rules_reasoning-0.2.0.dist-info/licenses/license
business_rules_reasoning-0.2.0.dist-info/RECORD
