Metadata-Version: 2.4
Name: business_rules_reasoning
Version: 0.2.0
Summary: A Python-based logical reasoning system combining rule-based engines with Large Language Models (LLMs) for business automation. Supports deduction and hypothesis testing, partial fact completion, and automated fact retrieval via documents or chat. Features include explainable reasoning, workflow integration, and customizable knowledge bases. Designed for transparency, efficiency, and seamless integration into decision-making workflows.
Project-URL: Homepage, https://github.com/lwardzala/business_rules_reasoning
Project-URL: Issues, https://github.com/lwardzala/business_rules_reasoning/issues
Author: Lukasz Wardzala <https://github.com/lwardzala>
License-Expression: MIT
License-File: license
Keywords: business rules,horn's inference,infernce engine,llm,llm inference,logical reasoning,reasoning
Classifier: Operating System :: OS Independent
Classifier: Programming Language :: Python :: 3
Requires-Python: >=3.8
